MANIFEST.in
README.md
setup.py
moneropy/__init__.py
moneropy/account.py
moneropy/base58.py
moneropy/cryptonote.py
moneropy/message.py
moneropy/mnemonic.py
moneropy/utils.py
moneropy/crypto/Keccak.py
moneropy/crypto/__init__.py
moneropy/crypto/ed25519.py
ph4_moneropy.egg-info/PKG-INFO
ph4_moneropy.egg-info/SOURCES.txt
ph4_moneropy.egg-info/dependency_links.txt
ph4_moneropy.egg-info/requires.txt
ph4_moneropy.egg-info/top_level.txt
tests/__init__.py
tests/context.py
tests/test_account.py
tests/test_base58.py
tests/test_cryptonote.py
tests/test_mnemonic.py
tests/test_utils.py
tests/testdata.py