Metadata-Version: 1.1
Name: ph4-moneropy
Version: 0.0.3
Summary: A python toolbox for Monero.
Home-page: https://github.com/monero-monitor/moneropy
Author: UNKNOWN
Author-email: UNKNOWN
License: BSD-3-Clause
Keywords: monero
Platform: UNKNOWN
Classifier: Development Status :: 2 - Pre-Alpha
Classifier: Topic :: Utilities
